orly/__init__.py
orly-0.1.0.dist-info/METADATA
orly-0.1.0.dist-info/WHEEL
orly-0.1.0.dist-info/top_level.txt
orly-0.1.0.dist-info/RECORD
