Metadata-Version: 2.4
Name: orly
Version: 0.1.0
Summary: This allows you to load modules in an elegant way.
Home-page: https://github.com/zZarby/orly
Author: Zarby
Author-email: 
Classifier: Programming Language :: Python :: 3
Classifier: License :: OSI Approved :: MIT License
Classifier: Operating System :: OS Independent
Requires-Python: >=3.8
Dynamic: author
Dynamic: classifier
Dynamic: description
Dynamic: description-content-type
Dynamic: home-page
Dynamic: requires-python
Dynamic: summary
